sierras.py
sierras-0.2.5.dist-info/LICENSE
sierras-0.2.5.dist-info/METADATA
sierras-0.2.5.dist-info/WHEEL
sierras-0.2.5.dist-info/top_level.txt
sierras-0.2.5.dist-info/RECORD
