Metadata-Version: 2.1
Name: sierras
Version: 0.2.5
Summary: A tool for empirical Arrhenius equation fitting for thermally-induced physicochemical processes.
Author-email: Francisco Fernandez <ffernandev@gmail.com>
License: MIT License
Project-URL: Homepage, https://github.com/fernandezfran/sierras
Keywords: arrhenius-process,arrhenius-equation,arrhenius-fitting,arrhenius-plot
Classifier: Development Status :: 4 - Beta
Classifier: Intended Audience :: Science/Research
Classifier: Operating System :: OS Independent
Classifier: Programming Language :: Python
Classifier: Programming Language :: Python :: 3.8
Classifier: Programming Language :: Python :: 3.9
Classifier: Programming Language :: Python :: 3.10
Classifier: Programming Language :: Python :: 3.11
Classifier: Topic :: Scientific/Engineering
License-File: LICENSE
Requires-Dist: importlib-metadata
Requires-Dist: matplotlib
Requires-Dist: numpy
Requires-Dist: pandas
Requires-Dist: scikit-learn
